apperror/__init__.py
apperror/app_error.py
apperror/http_status.py
apperror/op_status.py
apperror/test_app_error.py
apperror/test_http_status.py
apperror/test_op_status.py
apperror/utils.py
apperror/num_case/__init__.py
apperror/num_case/case_factory.py
apperror/num_case/code_mapper.py
apperror/num_case/num_case.py
apperror/num_case/num_range.py
apperror/num_case/test_case_factory.py
apperror/num_case/test_code_mapper.py
apperror/num_case/test_num_range.py
apperror_py-0.2.1.dist-info/licenses/LICENSE
apperror_py-0.2.1.dist-info/METADATA
apperror_py-0.2.1.dist-info/WHEEL
apperror_py-0.2.1.dist-info/top_level.txt
apperror_py-0.2.1.dist-info/RECORD
