Metadata-Version: 2.4
Name: apperror-py
Version: 0.2.1
Summary: Add your description here
Home-page: https://github.com/one2x-ai/AppError-py
Author: ikonglong
Author-email: chenlong@one2x.ai
Requires-Python: >=3.10.9
License-File: LICENSE
Dynamic: author
Dynamic: author-email
Dynamic: home-page
Dynamic: license-file
Dynamic: requires-python
